volmdlr.libs/libstdc++-8baf04f9.so.6.0.28
volmdlr.libs/libgcc_s-8b50eaaa.so.1
volmdlr/core.py
volmdlr/faces.py
volmdlr/discrete_representation_compiled.cpython-39-i386-linux-gnu.so
volmdlr/cloud.py
volmdlr/stl.py
volmdlr/core_compiled.pyx
volmdlr/display.py
volmdlr/geometry.py
volmdlr/discrete_representation.py
volmdlr/edges.py
volmdlr/wires.py
volmdlr/discrete_representation_compiled.cpp
volmdlr/surfaces.py
volmdlr/__init__.py
volmdlr/primitives3d.py
volmdlr/step.py
volmdlr/primitives2d.py
volmdlr/primitives.py
volmdlr/discrete_representation_compiled.py
volmdlr/cad_simplification.py
volmdlr/curves.py
volmdlr/gmsh_vm.py
volmdlr/core_compiled.cpython-39-i386-linux-gnu.so
volmdlr/shells.py
volmdlr/mesh.py
volmdlr/grid.py
volmdlr/templates.py
volmdlr/models/contours.py
volmdlr/models/bspline_curves.py
volmdlr/models/open_rounded_line_segments.py
volmdlr/models/casing.py
volmdlr/models/edges.py
volmdlr/models/bspline_surfaces.py
volmdlr/models/__init__.py
volmdlr/models/curves.py
volmdlr/models/cylindrical_surfaces.py
volmdlr/models/conical_surfaces.py
volmdlr/assets/logos/volmdlr.jpg
volmdlr/assets/js/babylon.js
volmdlr/assets/js/pep.js
volmdlr/assets/js/earcut.min.js
volmdlr/assets/js/babylonjs.loaders.min.js
volmdlr/utils/common_operations.py
volmdlr/utils/intersections.py
volmdlr/utils/parametric.py
volmdlr/utils/__init__.py
volmdlr/utils/step_writer.py
volmdlr/utils/step_reader.py
volmdlr/nurbs/operations.py
volmdlr/nurbs/fitting.cpython-39-i386-linux-gnu.so
volmdlr/nurbs/helpers.cpython-39-i386-linux-gnu.so
volmdlr/nurbs/core.cpp
volmdlr/nurbs/__init__.py
volmdlr/nurbs/core.cpython-39-i386-linux-gnu.so
volmdlr/nurbs/fitting.cpp
volmdlr/nurbs/helpers.cpp
volmdlr/nurbs/fitting.py
volmdlr-0.15.2.dist-info/WHEEL
volmdlr-0.15.2.dist-info/LICENSE
volmdlr-0.15.2.dist-info/RECORD
volmdlr-0.15.2.dist-info/top_level.txt
volmdlr-0.15.2.dist-info/METADATA
