Metadata-Version: 2.1
Name: volmdlr
Version: 0.15.2
Summary: A volume modeler computation-oriented. Include rendering bindings.
Home-page: https://github.com/Dessia-tech/volmdlr
Author: DessiA Technologies
Author-email: root@dessia.tech
License: Creative Commons Attribution-Share Alike license
Keywords: volume,modeler,CAD
Classifier: Topic :: Scientific/Engineering
Classifier: Topic :: Multimedia :: Graphics :: 3D Modeling
Classifier: Development Status :: 5 - Production/Stable
Requires-Python: >=3.9
License-File: LICENSE
Requires-Dist: packaging
Requires-Dist: dessia-common >=0.10.0
Requires-Dist: Cython >=3.0.0
Requires-Dist: numpy
Requires-Dist: matplotlib
Requires-Dist: scipy
Requires-Dist: geomdl
Requires-Dist: networkx
Requires-Dist: triangle
Requires-Dist: plot-data >=0.10.9
Requires-Dist: kaitaistruct
Requires-Dist: binaryornot
Requires-Dist: sympy
Requires-Dist: trimesh
Requires-Dist: rtree
Requires-Dist: gmsh
Requires-Dist: pyfqmr
Provides-Extra: doc
Requires-Dist: sphinx ; extra == 'doc'
Requires-Dist: nbsphinx ; extra == 'doc'
Requires-Dist: pydata-sphinx-theme ; extra == 'doc'
Requires-Dist: nbformat ; extra == 'doc'
Requires-Dist: nbconvert ; extra == 'doc'
Requires-Dist: sphinx-copybutton ; extra == 'doc'
Requires-Dist: sphinx-design ; extra == 'doc'
Provides-Extra: test
Requires-Dist: coverage ; extra == 'test'
